bytecode/__init__.py
bytecode/bytecode.py
bytecode/cfg.py
bytecode/concrete.py
bytecode/flags.py
bytecode/instr.py
bytecode/peephole_opt.py
bytecode/tests/__init__.py
bytecode/tests/test_bytecode.py
bytecode/tests/test_cfg.py
bytecode/tests/test_code.py
bytecode/tests/test_concrete.py
bytecode/tests/test_flags.py
bytecode/tests/test_instr.py
bytecode/tests/test_misc.py
bytecode/tests/test_peephole_opt.py
coz_bytecode-0.5.1.dist-info/DESCRIPTION.rst
coz_bytecode-0.5.1.dist-info/METADATA
coz_bytecode-0.5.1.dist-info/RECORD
coz_bytecode-0.5.1.dist-info/WHEEL
coz_bytecode-0.5.1.dist-info/metadata.json
coz_bytecode-0.5.1.dist-info/top_level.txt
