Metadata-Version: 2.0
Name: coz-bytecode
Version: 0.5.1
Summary: Python module to generate and modify bytecode (Temporary CoZ Fork)
Home-page: https://github.com/localhuman/bytecode
Author: Victor Stinner
Author-email: victor.stinner@gmail.com
License: MIT license
Platform: UNKNOWN
Classifier: Development Status :: 4 - Beta
Classifier: Intended Audience :: Developers
Classifier: License :: OSI Approved :: MIT License
Classifier: Natural Language :: English
Classifier: Operating System :: OS Independent
Classifier: Programming Language :: Python :: 3
Classifier: Topic :: Software Development :: Libraries :: Python Modules
Requires-Dist: aenum (>=2.0)
